[
  {
    "box": [
      761,
      121,
      1043,
      148
    ],
    "text": "ESTIMATED BUDGET",
    "label": null,
    "words": [
      {
        "box": [
          769,
          121,
          925,
          149
        ],
        "text": "ESTIMATED"
      },
      {
        "box": [
          938,
          121,
          1042,
          149
        ],
        "text": "BUDGET"
      }
    ]
  },
  {
    "box": [
      872,
      155,
      917,
      186
    ],
    "text": "for",
    "label": null,
    "words": [
      {
        "box": [
          875,
          154,
          914,
          185
        ],
        "text": "for"
      }
    ]
  },
  {
    "box": [
      546,
      186,
      1256,
      223
    ],
    "text": "Nutrition Education of Physicians Proposal",
    "label": null,
    "words": [
      {
        "box": [
          549,
          187,
          708,
          220
        ],
        "text": "Nutrition"
      },
      {
        "box": [
          720,
          188,
          875,
          220
        ],
        "text": "Education"
      },
      {
        "box": [
          890,
          189,
          927,
          220
        ],
        "text": "of"
      },
      {
        "box": [
          939,
          190,
          1112,
          222
        ],
        "text": "Physicians"
      },
      {
        "box": [
          1124,
          191,
          1255,
          224
        ],
        "text": "Proposal"
      }
    ]
  },
  {
    "box": [
      818,
      256,
      1006,
      287
    ],
    "text": "SECOND YEAR",
    "label": null,
    "words": [
      {
        "box": [
          823,
          258,
          922,
          288
        ],
        "text": "SECOND"
      },
      {
        "box": [
          941,
          258,
          1006,
          287
        ],
        "text": "YEAR"
      }
    ]
  },
  {
    "box": [
      572,
      288,
      1150,
      323
    ],
    "text": "(January 1, 1986-December 31, 1986)",
    "label": null,
    "words": [
      {
        "box": [
          572,
          289,
          708,
          323
        ],
        "text": "(January"
      },
      {
        "box": [
          722,
          291,
          760,
          323
        ],
        "text": "1,"
      },
      {
        "box": [
          773,
          292,
          993,
          324
        ],
        "text": "1986-December"
      },
      {
        "box": [
          1008,
          291,
          1064,
          324
        ],
        "text": "31,"
      },
      {
        "box": [
          1073,
          291,
          1149,
          324
        ],
        "text": "1986)"
      }
    ]
  },
  {
    "box": [
      180,
      462,
      339,
      491
    ],
    "text": "Personnel",
    "label": null,
    "words": [
      {
        "box": [
          182,
          464,
          337,
          491
        ],
        "text": "Personnel"
      }
    ]
  },
  {
    "box": [
      1084,
      499,
      1199,
      527
    ],
    "text": "Fringe",
    "label": null,
    "words": [
      {
        "box": [
          1088,
          499,
          1192,
          527
        ],
        "text": "Fringe"
      }
    ]
  },
  {
    "box": [
      550,
      530,
      640,
      560
    ],
    "text": "Title",
    "label": null,
    "words": [
      {
        "box": [
          552,
          530,
          639,
          560
        ],
        "text": "Title"
      }
    ]
  },
  {
    "box": [
      885,
      528,
      993,
      560
    ],
    "text": "Salary",
    "label": null,
    "words": [
      {
        "box": [
          889,
          531,
          993,
          559
        ],
        "text": "Salary"
      }
    ]
  },
  {
    "box": [
      1085,
      528,
      1225,
      563
    ],
    "text": "Benefits",
    "label": null,
    "words": [
      {
        "box": [
          1089,
          531,
          1225,
          563
        ],
        "text": "Benefits"
      }
    ]
  },
  {
    "box": [
      1320,
      531,
      1410,
      560
    ],
    "text": "Total",
    "label": null,
    "words": [
      {
        "box": [
          1325,
          532,
          1410,
          560
        ],
        "text": "Total"
      }
    ]
  },
  {
    "box": [
      182,
      561,
      448,
      593
    ],
    "text": "B. Levine, Ph.D.",
    "label": null,
    "words": [
      {
        "box": [
          182,
          564,
          218,
          592
        ],
        "text": "B."
      },
      {
        "box": [
          229,
          563,
          355,
          593
        ],
        "text": "Levine,"
      },
      {
        "box": [
          366,
          562,
          449,
          594
        ],
        "text": "Ph.D."
      }
    ]
  },
  {
    "box": [
      549,
      559,
      703,
      590
    ],
    "text": "Nutrition",
    "label": null,
    "words": [
      {
        "box": [
          549,
          560,
          704,
          589
        ],
        "text": "Nutrition"
      }
    ]
  },
  {
    "box": [
      776,
      557,
      821,
      586
    ],
    "text": "TO",
    "label": null,
    "words": [
      {
        "box": [
          790,
          556,
          819,
          585
        ],
        "text": "TO"
      }
    ]
  },
  {
    "box": [
      881,
      559,
      999,
      594
    ],
    "text": "$3, 658.",
    "label": null,
    "words": [
      {
        "box": [
          890,
          560,
          933,
          594
        ],
        "text": "$3,"
      },
      {
        "box": [
          940,
          561,
          1001,
          593
        ],
        "text": "658."
      }
    ]
  },
  {
    "box": [
      1086,
      561,
      1206,
      595
    ],
    "text": "$1,024.",
    "label": null,
    "words": [
      {
        "box": [
          1090,
          561,
          1206,
          594
        ],
        "text": "$1,024."
      }
    ]
  },
  {
    "box": [
      1317,
      562,
      1436,
      596
    ],
    "text": "$4, 682.",
    "label": null,
    "words": [
      {
        "box": [
          1325,
          564,
          1371,
          594
        ],
        "text": "$4,"
      },
      {
        "box": [
          1377,
          564,
          1437,
          596
        ],
        "text": "682."
      }
    ]
  },
  {
    "box": [
      544,
      599,
      688,
      625
    ],
    "text": "Director",
    "label": null,
    "words": [
      {
        "box": [
          549,
          599,
          686,
          624
        ],
        "text": "Director"
      }
    ]
  },
  {
    "box": [
      178,
      663,
      339,
      693
    ],
    "text": "M. Wigren",
    "label": null,
    "words": [
      {
        "box": [
          178,
          664,
          222,
          694
        ],
        "text": "M."
      },
      {
        "box": [
          228,
          664,
          336,
          693
        ],
        "text": "Wigren"
      }
    ]
  },
  {
    "box": [
      546,
      660,
      706,
      697
    ],
    "text": "Secretary",
    "label": null,
    "words": [
      {
        "box": [
          552,
          663,
          705,
          697
        ],
        "text": "Secretary"
      }
    ]
  },
  {
    "box": [
      788,
      666,
      823,
      692
    ],
    "text": "50",
    "label": null,
    "words": [
      {
        "box": [
          788,
          665,
          822,
          691
        ],
        "text": "50"
      }
    ]
  },
  {
    "box": [
      883,
      661,
      1005,
      695
    ],
    "text": "10, 350.",
    "label": null,
    "words": [
      {
        "box": [
          889,
          663,
          936,
          695
        ],
        "text": "10,"
      },
      {
        "box": [
          940,
          665,
          1004,
          695
        ],
        "text": "350."
      }
    ]
  },
  {
    "box": [
      1101,
      662,
      1202,
      697
    ],
    "text": "2, 277 .",
    "label": null,
    "words": [
      {
        "box": [
          1106,
          663,
          1134,
          697
        ],
        "text": "2,"
      },
      {
        "box": [
          1140,
          664,
          1188,
          696
        ],
        "text": "277"
      },
      {
        "box": [
          1193,
          664,
          1203,
          696
        ],
        "text": "."
      }
    ]
  },
  {
    "box": [
      1320,
      662,
      1436,
      698
    ],
    "text": "12,627.",
    "label": null,
    "words": [
      {
        "box": [
          1326,
          663,
          1436,
          698
        ],
        "text": "12,627."
      }
    ]
  },
  {
    "box": [
      179,
      732,
      515,
      763
    ],
    "text": "R. Tannenbaum, Ph.D.",
    "label": null,
    "words": [
      {
        "box": [
          181,
          733,
          220,
          762
        ],
        "text": "R."
      },
      {
        "box": [
          233,
          734,
          423,
          763
        ],
        "text": "Tannenbaum,"
      },
      {
        "box": [
          432,
          734,
          514,
          763
        ],
        "text": "Ph.D."
      }
    ]
  },
  {
    "box": [
      524,
      729,
      671,
      767
    ],
    "text": "Program",
    "label": null,
    "words": [
      {
        "box": [
          550,
          732,
          672,
          764
        ],
        "text": "Program"
      }
    ]
  },
  {
    "box": [
      903,
      732,
      1005,
      765
    ],
    "text": "2,000.",
    "label": null,
    "words": [
      {
        "box": [
          907,
          734,
          1007,
          766
        ],
        "text": "2,000."
      }
    ]
  },
  {
    "box": [
      1337,
      732,
      1439,
      767
    ],
    "text": "2,000.",
    "label": null,
    "words": [
      {
        "box": [
          1344,
          733,
          1439,
          766
        ],
        "text": "2,000."
      }
    ]
  },
  {
    "box": [
      550,
      766,
      698,
      795
    ],
    "text": "Evaluator",
    "label": null,
    "words": [
      {
        "box": [
          550,
          768,
          699,
          795
        ],
        "text": "Evaluator"
      }
    ]
  },
  {
    "box": [
      1324,
      766,
      1435,
      800
    ],
    "text": "19,309.",
    "label": null,
    "words": [
      {
        "box": [
          1326,
          767,
          1436,
          801
        ],
        "text": "19,309."
      }
    ]
  },
  {
    "box": [
      182,
      936,
      541,
      969
    ],
    "text": "Supplies and Services",
    "label": null,
    "words": [
      {
        "box": [
          182,
          936,
          322,
          969
        ],
        "text": "Supplies"
      },
      {
        "box": [
          332,
          936,
          390,
          969
        ],
        "text": "and"
      },
      {
        "box": [
          398,
          936,
          541,
          970
        ],
        "text": "Services"
      }
    ]
  },
  {
    "box": [
      181,
      1002,
      672,
      1037
    ],
    "text": "Printing and paper supply for",
    "label": null,
    "words": [
      {
        "box": [
          182,
          1003,
          321,
          1037
        ],
        "text": "Printing"
      },
      {
        "box": [
          331,
          1006,
          387,
          1037
        ],
        "text": "and"
      },
      {
        "box": [
          398,
          1006,
          488,
          1037
        ],
        "text": "paper"
      },
      {
        "box": [
          500,
          1006,
          606,
          1037
        ],
        "text": "supply"
      },
      {
        "box": [
          620,
          1005,
          673,
          1036
        ],
        "text": "for"
      }
    ]
  },
  {
    "box": [
      1321,
      1000,
      1442,
      1038
    ],
    "text": "30,000.",
    "label": null,
    "words": [
      {
        "box": [
          1327,
          1001,
          1443,
          1035
        ],
        "text": "30,000."
      }
    ]
  },
  {
    "box": [
      185,
      1033,
      984,
      1071
    ],
    "text": "\"Current Concepts and Perspectives in Nutrition\"",
    "label": null,
    "words": [
      {
        "box": [
          185,
          1036,
          320,
          1069
        ],
        "text": "\"Current"
      },
      {
        "box": [
          330,
          1037,
          469,
          1071
        ],
        "text": "Concepts"
      },
      {
        "box": [
          482,
          1038,
          538,
          1071
        ],
        "text": "and"
      },
      {
        "box": [
          549,
          1038,
          757,
          1071
        ],
        "text": "Perspectives"
      },
      {
        "box": [
          772,
          1037,
          806,
          1071
        ],
        "text": "in"
      },
      {
        "box": [
          819,
          1037,
          984,
          1070
        ],
        "text": "Nutrition\""
      }
    ]
  },
  {
    "box": [
      190,
      1069,
      1180,
      1108
    ],
    "text": "distributed to 40,000 M.D.s per issue, @ 4 issues per year)",
    "label": null,
    "words": [
      {
        "box": [
          199,
          1073,
          386,
          1104
        ],
        "text": "distributed"
      },
      {
        "box": [
          400,
          1073,
          435,
          1104
        ],
        "text": "to"
      },
      {
        "box": [
          450,
          1073,
          552,
          1105
        ],
        "text": "40,000"
      },
      {
        "box": [
          563,
          1073,
          655,
          1106
        ],
        "text": "M.D.s"
      },
      {
        "box": [
          666,
          1073,
          722,
          1107
        ],
        "text": "per"
      },
      {
        "box": [
          738,
          1073,
          843,
          1107
        ],
        "text": "issue,"
      },
      {
        "box": [
          855,
          1073,
          876,
          1108
        ],
        "text": "@"
      },
      {
        "box": [
          890,
          1073,
          909,
          1108
        ],
        "text": "4"
      },
      {
        "box": [
          923,
          1073,
          1026,
          1108
        ],
        "text": "issues"
      },
      {
        "box": [
          1038,
          1074,
          1091,
          1108
        ],
        "text": "per"
      },
      {
        "box": [
          1106,
          1074,
          1181,
          1108
        ],
        "text": "year)"
      }
    ]
  },
  {
    "box": [
      177,
      1137,
      675,
      1175
    ],
    "text": "Royalty cost for mailing list",
    "label": null,
    "words": [
      {
        "box": [
          179,
          1141,
          301,
          1172
        ],
        "text": "Royalty"
      },
      {
        "box": [
          313,
          1142,
          388,
          1172
        ],
        "text": "cost"
      },
      {
        "box": [
          400,
          1141,
          452,
          1173
        ],
        "text": "for"
      },
      {
        "box": [
          462,
          1141,
          588,
          1175
        ],
        "text": "mailing"
      },
      {
        "box": [
          603,
          1140,
          675,
          1176
        ],
        "text": "list"
      }
    ]
  },
  {
    "box": [
      1343,
      1141,
      1441,
      1171
    ],
    "text": "1,040.",
    "label": null,
    "words": [
      {
        "box": [
          1342,
          1139,
          1439,
          1171
        ],
        "text": "1,040."
      }
    ]
  },
  {
    "box": [
      212,
      1174,
      446,
      1204
    ],
    "text": "($6.50/1, 000) *",
    "label": null,
    "words": [
      {
        "box": [
          218,
          1175,
          361,
          1205
        ],
        "text": "($6.50/1,"
      },
      {
        "box": [
          365,
          1177,
          429,
          1205
        ],
        "text": "000)"
      },
      {
        "box": [
          433,
          1175,
          446,
          1205
        ],
        "text": "*"
      }
    ]
  },
  {
    "box": [
      179,
      1240,
      296,
      1272
    ],
    "text": "Postage",
    "label": null,
    "words": [
      {
        "box": [
          179,
          1240,
          296,
          1269
        ],
        "text": "Postage"
      }
    ]
  },
  {
    "box": [
      1342,
      1241,
      1441,
      1275
    ],
    "text": "8,320.",
    "label": null,
    "words": [
      {
        "box": [
          1342,
          1241,
          1443,
          1274
        ],
        "text": "8,320."
      }
    ]
  },
  {
    "box": [
      215,
      1275,
      418,
      1303
    ],
    "text": "($52. /1000)*",
    "label": null,
    "words": [
      {
        "box": [
          218,
          1278,
          295,
          1306
        ],
        "text": "($52."
      },
      {
        "box": [
          299,
          1277,
          418,
          1303
        ],
        "text": "/1000)*"
      }
    ]
  },
  {
    "box": [
      172,
      1338,
      906,
      1379
    ],
    "text": "Addressing and handling by Mail Order House",
    "label": null,
    "words": [
      {
        "box": [
          180,
          1342,
          351,
          1374
        ],
        "text": "Addressing"
      },
      {
        "box": [
          367,
          1342,
          418,
          1375
        ],
        "text": "and"
      },
      {
        "box": [
          429,
          1342,
          570,
          1377
        ],
        "text": "handling"
      },
      {
        "box": [
          583,
          1342,
          621,
          1378
        ],
        "text": "by"
      },
      {
        "box": [
          634,
          1342,
          707,
          1378
        ],
        "text": "Mail"
      },
      {
        "box": [
          720,
          1342,
          805,
          1379
        ],
        "text": "Order"
      },
      {
        "box": [
          821,
          1343,
          906,
          1379
        ],
        "text": "House"
      }
    ]
  },
  {
    "box": [
      1335,
      1339,
      1437,
      1375
    ],
    "text": "6, 400.",
    "label": null,
    "words": [
      {
        "box": [
          1341,
          1341,
          1373,
          1375
        ],
        "text": "6,"
      },
      {
        "box": [
          1379,
          1341,
          1437,
          1376
        ],
        "text": "400."
      }
    ]
  },
  {
    "box": [
      217,
      1373,
      415,
      1405
    ],
    "text": "($40./1000) *",
    "label": null,
    "words": [
      {
        "box": [
          218,
          1374,
          393,
          1406
        ],
        "text": "($40./1000)"
      },
      {
        "box": [
          399,
          1374,
          414,
          1406
        ],
        "text": "*"
      }
    ]
  },
  {
    "box": [
      1322,
      1371,
      1441,
      1412
    ],
    "text": "45 , 760.",
    "label": null,
    "words": [
      {
        "box": [
          1327,
          1373,
          1355,
          1409
        ],
        "text": "45"
      },
      {
        "box": [
          1363,
          1375,
          1371,
          1410
        ],
        "text": ","
      },
      {
        "box": [
          1379,
          1376,
          1442,
          1411
        ],
        "text": "760."
      }
    ]
  },
  {
    "box": [
      831,
      1507,
      1086,
      1547
    ],
    "text": "Total Personnel",
    "label": null,
    "words": [
      {
        "box": [
          836,
          1508,
          929,
          1542
        ],
        "text": "Total"
      },
      {
        "box": [
          937,
          1511,
          1086,
          1546
        ],
        "text": "Personnel"
      }
    ]
  },
  {
    "box": [
      1322,
      1511,
      1435,
      1542
    ],
    "text": "19,309.",
    "label": null,
    "words": [
      {
        "box": [
          1326,
          1513,
          1435,
          1542
        ],
        "text": "19,309."
      }
    ]
  },
  {
    "box": [
      833,
      1543,
      1257,
      1581
    ],
    "text": "Total Supplies & Services",
    "label": null,
    "words": [
      {
        "box": [
          838,
          1545,
          928,
          1578
        ],
        "text": "Total"
      },
      {
        "box": [
          938,
          1545,
          1079,
          1579
        ],
        "text": "Supplies"
      },
      {
        "box": [
          1089,
          1546,
          1112,
          1580
        ],
        "text": "&"
      },
      {
        "box": [
          1122,
          1546,
          1257,
          1582
        ],
        "text": "Services"
      }
    ]
  },
  {
    "box": [
      1325,
      1543,
      1436,
      1579
    ],
    "text": "45,760.",
    "label": null,
    "words": [
      {
        "box": [
          1327,
          1546,
          1435,
          1579
        ],
        "text": "45,760."
      }
    ]
  },
  {
    "box": [
      834,
      1576,
      1162,
      1614
    ],
    "text": "Indirect Costs (208)",
    "label": null,
    "words": [
      {
        "box": [
          838,
          1578,
          977,
          1609
        ],
        "text": "Indirect"
      },
      {
        "box": [
          989,
          1579,
          1079,
          1611
        ],
        "text": "Costs"
      },
      {
        "box": [
          1096,
          1580,
          1162,
          1614
        ],
        "text": "(208)"
      }
    ]
  },
  {
    "box": [
      1319,
      1582,
      1437,
      1610
    ],
    "text": "13,014.",
    "label": null,
    "words": [
      {
        "box": [
          1327,
          1583,
          1436,
          1611
        ],
        "text": "13,014."
      }
    ]
  },
  {
    "box": [
      1119,
      1647,
      1212,
      1680
    ],
    "text": "TOTAL",
    "label": null,
    "words": [
      {
        "box": [
          1124,
          1648,
          1210,
          1678
        ],
        "text": "TOTAL"
      }
    ]
  },
  {
    "box": [
      1307,
      1647,
      1442,
      1682
    ],
    "text": "$78, 083.",
    "label": null,
    "words": [
      {
        "box": [
          1312,
          1648,
          1374,
          1681
        ],
        "text": "$78,"
      },
      {
        "box": [
          1379,
          1649,
          1443,
          1681
        ],
        "text": "083."
      }
    ]
  },
  {
    "box": [
      179,
      1879,
      1498,
      1919
    ],
    "text": "*Figures represent cost of distributing 40,000 copies of \"Current Concepts and",
    "label": null,
    "words": [
      {
        "box": [
          180,
          1881,
          320,
          1914
        ],
        "text": "*Figures"
      },
      {
        "box": [
          331,
          1881,
          487,
          1916
        ],
        "text": "represent"
      },
      {
        "box": [
          496,
          1882,
          570,
          1916
        ],
        "text": "cost"
      },
      {
        "box": [
          581,
          1882,
          621,
          1916
        ],
        "text": "of"
      },
      {
        "box": [
          634,
          1882,
          842,
          1918
        ],
        "text": "distributing"
      },
      {
        "box": [
          857,
          1883,
          961,
          1918
        ],
        "text": "40,000"
      },
      {
        "box": [
          972,
          1883,
          1077,
          1919
        ],
        "text": "copies"
      },
      {
        "box": [
          1088,
          1883,
          1128,
          1919
        ],
        "text": "of"
      },
      {
        "box": [
          1139,
          1883,
          1281,
          1919
        ],
        "text": "\"Current"
      },
      {
        "box": [
          1292,
          1883,
          1434,
          1920
        ],
        "text": "Concepts"
      },
      {
        "box": [
          1445,
          1884,
          1498,
          1920
        ],
        "text": "and"
      }
    ]
  },
  {
    "box": [
      181,
      1913,
      937,
      1951
    ],
    "text": "Perspectives in Nutrition\" four times a year.",
    "label": null,
    "words": [
      {
        "box": [
          182,
          1917,
          383,
          1947
        ],
        "text": "Perspectives"
      },
      {
        "box": [
          401,
          1916,
          432,
          1948
        ],
        "text": "in"
      },
      {
        "box": [
          445,
          1916,
          619,
          1949
        ],
        "text": "Nutrition\""
      },
      {
        "box": [
          636,
          1916,
          704,
          1950
        ],
        "text": "four"
      },
      {
        "box": [
          720,
          1916,
          807,
          1951
        ],
        "text": "times"
      },
      {
        "box": [
          821,
          1917,
          838,
          1951
        ],
        "text": "a"
      },
      {
        "box": [
          855,
          1917,
          936,
          1952
        ],
        "text": "year."
      }
    ]
  }
]